Metadata-Version: 2.1
Name: Gaus_dotgb_Bin
Version: 0.1
Summary: Gaussian and Binomial distributions
Author: dotgb
Author-email: myemail@something.com
